secretstorage/__init__.py
secretstorage/collection.py
secretstorage/defines.py
secretstorage/dhcrypto.py
secretstorage/exceptions.py
secretstorage/item.py
secretstorage/py.typed
secretstorage/util.py
SecretStorage-3.3.2.dist-info/LICENSE
SecretStorage-3.3.2.dist-info/METADATA
SecretStorage-3.3.2.dist-info/WHEEL
SecretStorage-3.3.2.dist-info/top_level.txt
SecretStorage-3.3.2.dist-info/RECORD
