Metadata-Version: 2.1
Name: SecretStorage
Version: 3.3.2
Summary: Python bindings to FreeDesktop.org Secret Service API
Home-page: https://github.com/mitya57/secretstorage
Author: Dmitry Shachnev
Author-email: mitya57@gmail.com
License: BSD 3-Clause License
Platform: Linux
Classifier: Development Status :: 5 - Production/Stable
Classifier: License :: OSI Approved :: BSD License
Classifier: Operating System :: POSIX
Classifier: Programming Language :: Python
Classifier: Programming Language :: Python :: 3 :: Only
Classifier: Programming Language :: Python :: 3.6
Classifier: Programming Language :: Python :: 3.7
Classifier: Programming Language :: Python :: 3.8
Classifier: Programming Language :: Python :: 3.9
Classifier: Programming Language :: Python :: 3.10
Classifier: Topic :: Security
Classifier: Topic :: Software Development :: Libraries :: Python Modules
Requires-Python: >=3.6
License-File: LICENSE
